gama_gymnasium/__init__.py
gama_gymnasium/exceptions.py
gama_gymnasium/gama_client_wrapper.py
gama_gymnasium/gama_env.py
gama_gymnasium/space_converter.py
gama_gymnasium-0.1.1.dist-info/METADATA
gama_gymnasium-0.1.1.dist-info/WHEEL
gama_gymnasium-0.1.1.dist-info/licenses/LICENSE
gama_gymnasium-0.1.1.dist-info/RECORD
