Metadata-Version: 2.4
Name: gama-gymnasium
Version: 0.1.1
Summary: A Gymnasium environment for reinforcement learning with GAMA agent-based simulations
Project-URL: Homepage, https://github.com/gama-platform/gama-gymnasium
Project-URL: Repository, https://github.com/gama-platform/gama-gymnasium
Project-URL: Bug Tracker, https://github.com/gama-platform/gama-gymnasium/issues
Project-URL: Documentation, https://github.com/gama-platform/gama-gymnasium#readme
Project-URL: GAMA Platform, https://gama-platform.org/
Author-email: Baptiste Lesquoy <baptiste.lesquoy@ird.fr>, Meritxell Vinyals <meritxell.vinyals@inrae.fr>
License: MIT License
License-File: LICENSE
Keywords: agent-based-modeling,gama,gymnasium,reinforcement-learning,rl,simulation
Classifier: Development Status :: 3 - Alpha
Classifier: Intended Audience :: Developers
Classifier: Intended Audience :: Science/Research
Classifier: License :: OSI Approved :: MIT License
Classifier: Operating System :: OS Independent
Classifier: Programming Language :: Python :: 3
Classifier: Programming Language :: Python :: 3.8
Classifier: Programming Language :: Python :: 3.9
Classifier: Programming Language :: Python :: 3.10
Classifier: Programming Language :: Python :: 3.11
Classifier: Programming Language :: Python :: 3.12
Classifier: Topic :: Scientific/Engineering :: Artificial Intelligence
Classifier: Topic :: Software Development :: Libraries :: Python Modules
Requires-Python: >=3.8
Requires-Dist: gama-client>=1.2.1
Requires-Dist: gymnasium>=0.27.0
Requires-Dist: numpy>=1.21.0
Provides-Extra: dev
Requires-Dist: black; extra == 'dev'
Requires-Dist: flake8; extra == 'dev'
Requires-Dist: isort; extra == 'dev'
Requires-Dist: pytest-cov; extra == 'dev'
Requires-Dist: pytest>=6.0; extra == 'dev'
Provides-Extra: examples
Requires-Dist: matplotlib>=3.3.0; extra == 'examples'
Requires-Dist: torch>=1.9.0; extra == 'examples'
